ptfgen/__init__.py
ptfgen/__main__.py
ptfgen/api_cmd.py
ptfgen/bind_cmd.py
ptfgen/command.py
ptfgen/constants.py
ptfgen/encoder.py
ptfgen/figma_cmd.py
ptfgen/file_helpers.py
ptfgen/json_cmd.py
ptfgen/mock_cmd.py
ptfgen/model.py
ptfgen/pb.py
ptfgen/str_helpers.py
ptfgen/template.py
ptfgen/template_cmd.py
ptfgen/test_cmd.py
ptfgen/vm.py
ptfgen_templates/__init__.py
ptfgen_templates/base/assembler.dart
ptfgen_templates/base/navigator.dart
ptfgen_templates/base/navigator_mock.dart
ptfgen_templates/base/usecase.dart
ptfgen_templates/base/usecase_mock.dart
ptfgen_templates/base/view.dart
ptfgen_templates/base/viewmodel.dart
ptfgen_templates/base/viewmodel_test.dart
ptfgen_templates/commands/api.dart
ptfgen_templates/commands/bindviewmodel.dart
ptfgen_templates/commands/json.dart
ptfgen_templates/commands/mock.dart
ptfgen_templates/commands/unit_test.dart
ptfgen-1.0.3.dist-info/LICENSE
ptfgen-1.0.3.dist-info/METADATA
ptfgen-1.0.3.dist-info/WHEEL
ptfgen-1.0.3.dist-info/entry_points.txt
ptfgen-1.0.3.dist-info/top_level.txt
ptfgen-1.0.3.dist-info/RECORD
