Metadata-Version: 2.1
Name: ptfgen
Version: 1.0.3
Summary: A code generator for Flutter
Home-page: https://github.com/tienpx-x/PTfGen
Author: Pham Xuan Tien
Author-email: tienpx.xxx@gmail.com
License: MIT
Platform: UNKNOWN
Classifier: Programming Language :: Python :: 3
Classifier: License :: OSI Approved :: MIT License
Classifier: Operating System :: OS Independent
Requires-Python: >=3
Requires-Dist: cssutils (>=2.2.0)
Requires-Dist: Jinja2 (>=2.10)
Requires-Dist: arghandler (>=1.2)
